LICENSE
README.md
pyproject.toml
gptcli/__init__.py
gptcli/assistant.py
gptcli/cli.py
gptcli/composite.py
gptcli/config.py
gptcli/cost.py
gptcli/gpt.py
gptcli/logging_utils.py
gptcli/openai_types.py
gptcli/persist.py
gptcli/session.py
gptcli/types.py
openai_assistants_cli.egg-info/PKG-INFO
openai_assistants_cli.egg-info/SOURCES.txt
openai_assistants_cli.egg-info/dependency_links.txt
openai_assistants_cli.egg-info/entry_points.txt
openai_assistants_cli.egg-info/requires.txt
openai_assistants_cli.egg-info/top_level.txt
tests/test_session.py
tests/test_term_utils.py