Metadata-Version: 2.1
Name: openai-assistants-cli
Version: 0.1.1
Summary: Command-line interface for ChatGPT Assistants: https://platform.openai.com/docs/assistants/overview
Author-email: Lyon Lay <lay.lyon@gmail.com>
License: Copyright (c) 2023 by Val Kharitonov
Project-URL: Homepage, https://github.com/grid-link-inc/gpt-cli
Keywords: cli,command-line,assistant,openai,gpt-3,gpt-4,llm,chatgpt,openai-assistants-cli,gpt-client
Classifier: Development Status :: 4 - Beta
Classifier: Environment :: Console
Classifier: Intended Audience :: Developers
Classifier: Intended Audience :: End Users/Desktop
Classifier: Intended Audience :: Science/Research
Classifier: License :: OSI Approved :: MIT License
Classifier: Topic :: Scientific/Engineering :: Artificial Intelligence
Requires-Python: >=3.9
License-File: LICENSE
Requires-Dist: attrs==23.1.0
Requires-Dist: black==23.1.0
Requires-Dist: openai==1.3.8
Requires-Dist: prompt-toolkit==3.0.41
Requires-Dist: pytest==7.3.1
Requires-Dist: PyYAML==6.0
Requires-Dist: rich==13.7.0
Requires-Dist: tiktoken==0.5.2
Requires-Dist: tokenizers==0.15.0
Requires-Dist: typing_extensions==4.5.0
